tanco/__init__.py
tanco/app.py
tanco/client.py
tanco/database.py
tanco/driver.py
tanco/model.py
tanco/orgtest.py
tanco/runner.py
tanco/testplan.org
tanco/sql/init.sql
tanco/static/firebase-cfg.mjs
tanco/static/htmx.js
tanco/static/htmx.min.js
tanco/static/login.mjs
tanco/static/style.css
tanco/templates/about.html
tanco/templates/attempt.html
tanco/templates/challenge.html
tanco/templates/challenges.html
tanco/templates/index.html
tanco/templates/login.html
tanco/templates/me.html
tanco/templates/pass.html
tanco/templates/please_login.html
tanco/templates/result.html
tanco/templates/state.html
tanco/templates/test.html
tanco/templates/websocket.html
tanco/templates/whoami.html
tanco-0.2.0.dist-info/licenses/LICENSE
tanco-0.2.0.dist-info/METADATA
tanco-0.2.0.dist-info/WHEEL
tanco-0.2.0.dist-info/entry_points.txt
tanco-0.2.0.dist-info/top_level.txt
tanco-0.2.0.dist-info/RECORD
