Metadata-Version: 2.4
Name: tanco
Version: 0.2.0
Summary: A tool for test-driven teaching.
Maintainer-email: Michal J Wallace <michal.wallace@gmail.com>
License-Expression: MIT
Project-URL: Homepage, https://tangentcode.com/
Project-URL: Source, https://github.com/tangentcode/tanco
Project-URL: Live Server, https://tanco.tangentcode.com/
Requires-Python: >=3.10
License-File: LICENSE
Requires-Dist: jwt~=1.3.1
Requires-Dist: requests~=2.31.0
Requires-Dist: quart~=0.19.4
Requires-Dist: hypercorn~=0.16.0
Requires-Dist: websockets~=12.0
Dynamic: license-file
